{"cameraMode":{"drawMode":0,"name":"Shaded","section":"Shading Mode"},"sceneLighting":true,"audioPlay":false,"sceneViewState":{"showFog":true,"showMaterialUpdate":false,"showSkybox":true,"showFlares":true,"showImageEffects":true,"showParticleSystems":true},"in2DMode":false,"pivot":{"x":-23.69933319091797,"y":23.771623611450197,"z":1.8577041625976563},"rotation":{"x":-0.16429223120212556,"y":-0.813937783241272,"z":0.2763544023036957,"w":-0.4839222729206085},"size":24.795242309570314,"orthographic":false}